mfs_styletts2
